multirepast4py/__init__.py
multirepast4py/network.py
multirepast4py-0.1.1.dist-info/LICENSE
multirepast4py-0.1.1.dist-info/METADATA
multirepast4py-0.1.1.dist-info/WHEEL
multirepast4py-0.1.1.dist-info/top_level.txt
multirepast4py-0.1.1.dist-info/RECORD
